nikitas_agents/__init__.py
nikitas_agents/agents.py
nikitas_agents/schema.py
nikitas_agents-0.1.0.dist-info/licenses/LICENSE
nikitas_agents-0.1.0.dist-info/METADATA
nikitas_agents-0.1.0.dist-info/WHEEL
nikitas_agents-0.1.0.dist-info/top_level.txt
nikitas_agents-0.1.0.dist-info/RECORD
