Metadata-Version: 2.4
Name: nikitas-agents
Version: 0.1.0
Summary: Provider-agnostic wrappers around OpenAI and Mistral SDKs to power LLM-based agents in games or simulations.
Author-email: Nikita Dmitrieff <nikita@example.com>
License: MIT License
Project-URL: Homepage, https://github.com/NikitaDmitrieff/nikitas-agents
Project-URL: Repository, https://github.com/NikitaDmitrieff/nikitas-agents
Requires-Python: >=3.9
License-File: LICENSE
Requires-Dist: python-dotenv>=1.0
Requires-Dist: openai>=1.0
Requires-Dist: mistralai>=0.3
Dynamic: license-file
